dodo_commands/__init__.py
dodo_commands/dodo.py
dodo_commands/bin/__init__.py
dodo_commands/bin/dodo_autocomplete.fish
dodo_commands/bin/dodo_autocomplete.sh
dodo_commands/dependencies/__init__.py
dodo_commands/dependencies/packages/six.py
dodo_commands/dependencies/packages/ansimarkup/__init__.py
dodo_commands/dependencies/packages/ansimarkup/__main__.py
dodo_commands/dependencies/packages/ansimarkup/ansi.py
dodo_commands/dependencies/packages/ansimarkup/compat.py
dodo_commands/dependencies/packages/ansimarkup/logformatter.py
dodo_commands/dependencies/packages/ansimarkup/markup.py
dodo_commands/dependencies/packages/ansimarkup/tags.py
dodo_commands/dependencies/packages/ansimarkup/test.py
dodo_commands/dependencies/packages/argcomplete/__init__.py
dodo_commands/dependencies/packages/argcomplete/_check_console_script.py
dodo_commands/dependencies/packages/argcomplete/_check_module.py
dodo_commands/dependencies/packages/argcomplete/compat.py
dodo_commands/dependencies/packages/argcomplete/completers.py
dodo_commands/dependencies/packages/argcomplete/my_argparse.py
dodo_commands/dependencies/packages/argcomplete/my_shlex.py
dodo_commands/dependencies/packages/argcomplete/shell_integration.py
dodo_commands/dependencies/packages/colorama/__init__.py
dodo_commands/dependencies/packages/colorama/ansi.py
dodo_commands/dependencies/packages/colorama/ansitowin32.py
dodo_commands/dependencies/packages/colorama/initialise.py
dodo_commands/dependencies/packages/colorama/win32.py
dodo_commands/dependencies/packages/colorama/winterm.py
dodo_commands/dependencies/packages/dotenv/__init__.py
dodo_commands/dependencies/packages/dotenv/cli.py
dodo_commands/dependencies/packages/dotenv/compat.py
dodo_commands/dependencies/packages/dotenv/ipython.py
dodo_commands/dependencies/packages/dotenv/main.py
dodo_commands/dependencies/packages/dotenv/parser.py
dodo_commands/dependencies/packages/dotenv/py.typed
dodo_commands/dependencies/packages/dotenv/version.py
dodo_commands-0.52.1.dist-info/LICENSE.txt
dodo_commands-0.52.1.dist-info/METADATA
dodo_commands-0.52.1.dist-info/WHEEL
dodo_commands-0.52.1.dist-info/entry_points.txt
dodo_commands-0.52.1.dist-info/top_level.txt
dodo_commands-0.52.1.dist-info/RECORD
