Metadata-Version: 2.1
Name: dodo-commands
Version: 0.52.1
Summary: Project-aware development environments, inspired by django-manage
Author-email: Maarten Nieber <hallomaarten@yahoo.com>
License: MIT
Project-URL: Homepage, https://github.com/mnieber/dodo-commands
Requires-Python: >=3.6
License-File: LICENSE.txt
